COPYING.txt
MANIFEST.in
README.txt
setup.cfg
setup.py
mock_http/__init__.py
mock_http.egg-info/PKG-INFO
mock_http.egg-info/SOURCES.txt
mock_http.egg-info/dependency_links.txt
mock_http.egg-info/entry_points.txt
mock_http.egg-info/not-zip-safe
mock_http.egg-info/requires.txt
mock_http.egg-info/top_level.txt
mock_http/docs/Makefile
mock_http/docs/source/conf.py
mock_http/docs/source/index.rst
mock_http/docs/source/modules/mock_http.rst
mock_http/tests/__init__.py
mock_http/tests/unit/__init__.py
mock_http/tests/unit/test_mock_http.py