Metadata-Version: 1.0
Name: mock-http
Version: 1.0
Summary: A mock http server for unit testing code that uses web services.
Home-page: https://github.com/oreillymedia/pymockhttpserver
Author: Nick Pilon
Author-email: npilon@oreilly.com
License: Apache 2
Platform: UNKNOWN
Classifier: Development Status :: 5 - Production/Stable
Classifier: Intended Audience :: Developers
Classifier: License :: OSI Approved :: Apache Software License
Classifier: Operating System :: OS Independent
Classifier: Programming Language :: Python
Classifier: Topic :: Internet :: WWW/HTTP
Classifier: Topic :: Software Development :: Testing
Classifier: Topic :: Software Development :: Libraries :: Python Modules
